gogym/__init__.py
gogym/api.py
gogym/config.py
gogym/control.py
gogym/core.py
gogym/underlying.py
gogym-1.1.dist-info/LICENSE
gogym-1.1.dist-info/METADATA
gogym-1.1.dist-info/WHEEL
gogym-1.1.dist-info/top_level.txt
gogym-1.1.dist-info/RECORD
